torch_nested/__init__.py
torch_nested/nested_size.py
torch_nested/nested_tensors.py
torch_nested/py.typed
torch_nested/str_repr.py
torch_nested/type_definitions.py
torch_nested/type_signals.py
torch_nested-0.0.5.dist-info/METADATA
torch_nested-0.0.5.dist-info/WHEEL
torch_nested-0.0.5.dist-info/top_level.txt
torch_nested-0.0.5.dist-info/RECORD
