Metadata-Version: 2.1
Name: torch_nested
Version: 0.0.5
Summary: Easily manipulate torch.Tensors inside highly nested data-structures.
Home-page: https://github.com/snimu/torch-nested
Author: Sebastian Nicolas Muller @snimu
Author-email: sebastian.nicolas.mueller@gmail.com
License: MIT
Keywords: torch pytorch nested torch-nested tensor tensors nested-tensors deep-learning ml
Classifier: License :: OSI Approved :: MIT License
Classifier: Operating System :: OS Independent
Classifier: Programming Language :: Python :: 3
Classifier: Programming Language :: Python :: 3 :: Only
Classifier: Programming Language :: Python :: 3.6
Classifier: Programming Language :: Python :: 3.7
Classifier: Programming Language :: Python :: 3.8
Classifier: Programming Language :: Python :: 3.9
Classifier: Programming Language :: Python :: 3.10
Classifier: Programming Language :: Python :: 3.11
Requires-Python: >=3.7
